tokenizer/__init__.py
tokenizer/determine_language.py
tokenizer/help_functions.py
tokenizer/sentence_finder.py
tokenizer/spellcheck.py
tokenizer/tokenize_sentence.py
tokenizer/tokenizer.py
tokenizer_cstm/__init__.py
tokenizer_cstm/determine_language.py
tokenizer_cstm/help_functions.py
tokenizer_cstm/sentence_finder.py
tokenizer_cstm/spellcheck.py
tokenizer_cstm/tokenize_sentence.py
tokenizer_cstm/tokenize_sentence_lower.py
tokenizer_cstm/tokenizer.py
tokenizer_cstm-0.7.dist-info/METADATA
tokenizer_cstm-0.7.dist-info/RECORD
tokenizer_cstm-0.7.dist-info/WHEEL
tokenizer_cstm-0.7.dist-info/top_level.txt
