Metadata-Version: 2.1
Name: tokenizer-cstm
Version: 0.7
Summary: fining sentences from raw text and tokenizing
Home-page: UNKNOWN
Author: Andrin Pelican
Author-email: andrin.pelican@bluewin.ch
License: UNKNOWN
Platform: UNKNOWN
